Workbook
Name aporte: Carteira!$D$23
Name redimento_carteira: Carteira!$C$17
Name salario: Carteira!$C$16

Sheet Carteira
B13: Configurações
B16: Salário | C16: 1500
B17: Rendimento Carteira | C17: 0.01
B18: Sugestão de Investimento | C18: =30%*salario -> 450
B23: Quanto investir por mês? | D23: =C18 -> 450
B24: Por quantos anos? | D24: 5
B25: Taxa de rendimento mensal? | D25: 0.01079
B26: Patrimônio acumulado? | D26: =FV(D25,D24*12,-D23) -> 37699.611
B27: Dividendos mensais? | D27: =D26*$C$17 -> 376.99611
A32: 2 | B32: Quanto em 2 anos? | C32: =FV($D$25,12*A32,-$D$23) -> 12252.432 | D32: =C32*$C$17 -> 122.52432
A33: 5 | B33: Quantos em 5 anos? | C33: =FV($D$25,12*A33,-$D$23) -> 37699.611 | D33: =C33*$C$17 -> 376.99611
A34: 10 | B34: Quantos em 10 anos? | C34: =FV($D$25,12*A34,-$D$23) -> 109477.9 | D34: =C34*$C$17 -> 1094.779
A35: 20 | B35: Quantos em 20 anos? | C35: =FV($D$25,12*A35,-$D$23) -> 506339.28 | D35: =C35*$C$17 -> 5063.3928
A36: 30 | B36: Quantos em 30 anos? | C36: =FV($D$25,12*A36,-$D$23) -> 1944976.3 | D36: =C36*$C$17 -> 19449.763
B38: Perfil | D38: MODERADO
B39: Valor a ser investido por mês | D39: =aporte -> 450
B41: TIPO DE FII | C41: Percentual sugerido | D41: Valores
B42: Papel | C42: =VLOOKUP($D$38&"-"&B42,'Banco de dados'!A3:D21,4,FALSE) -> 0.32 | D42: =VLOOKUP($D$38&"-"&B42,'Banco de dados'!A3:D21,4,FALSE) *$D$39 -> 144
B43: Tijolo | C43: =VLOOKUP($D$38&"-"&B43,'Banco de dados'!A4:D22,4,FALSE) -> 0.4 | D43: =VLOOKUP($D$38&"-"&B43,'Banco de dados'!A4:D22,4,FALSE) *$D$39 -> 180
B44: Híbridos | C44: =VLOOKUP($D$38&"-"&B44,'Banco de dados'!A5:D23,4,FALSE) -> 0.08 | D44: =VLOOKUP($D$38&"-"&B44,'Banco de dados'!A5:D23,4,FALSE) *$D$39 -> 36
B45: FOFs | C45: =VLOOKUP($D$38&"-"&B45,'Banco de dados'!A6:D24,4,FALSE) -> 0.1 | D45: =VLOOKUP($D$38&"-"&B45,'Banco de dados'!A6:D24,4,FALSE) *$D$39 -> 45
B46: Desenvolvimento | C46: =VLOOKUP($D$38&"-"&B46,'Banco de dados'!A7:D25,4,FALSE) -> 0.05 | D46: =VLOOKUP($D$38&"-"&B46,'Banco de dados'!A7:D25,4,FALSE) *$D$39 -> 22.5
B47: Hotelarias | C47: =VLOOKUP($D$38&"-"&B47,'Banco de dados'!A8:D26,4,FALSE) -> 0.05 | D47: =VLOOKUP($D$38&"-"&B47,'Banco de dados'!A8:D26,4,FALSE) *$D$39 -> 22.5
D48: =SUM(D42:D47) -> 450

Sheet Banco de dados
A3: Chave | B3: Perfil | C3: Tipos de FIIs | D3: %
A4: CONSERVADOR-Papel | B4: Conservador | C4: Papel | D4: 0.3
A5: CONSERVADOR-Tijolo | B5: Conservador | C5: Tijolo | D5: 0.5
A6: CONSERVADOR-Híbridos | B6: Conservador | C6: Híbridos | D6: 0.1
A7: CONSERVADOR-FOFs | B7: Conservador | C7: FOFs | D7: 0.1
A8: CONSERVADOR-Desenvolvimento | B8: Conservador | C8: Desenvolvimento | D8: 0
A9: CONSERVADOR-Hotelarias | B9: Conservador | C9: Hotelarias | D9: 0
A10: =B10&"-"&C10 -> Moderado-Papel | B10: Moderado | C10: Papel | D10: 0.32
A11: =B11&"-"&C11 -> Moderado-Tijolo | B11: Moderado | C11: Tijolo | D11: 0.4
A12: =B12&"-"&C12 -> Moderado-Híbridos | B12: Moderado | C12: Híbridos | D12: 0.08
A13: =B13&"-"&C13 -> Moderado-FOFs | B13: Moderado | C13: FOFs | D13: 0.1
A14: =B14&"-"&C14 -> Moderado-Desenvolvimento | B14: Moderado | C14: Desenvolvimento | D14: 0.05
A15: =B15&"-"&C15 -> Moderado-Hotelarias | B15: Moderado | C15: Hotelarias | D15: 0.05
A16: =B16&"-"&C16 -> Agressivo-Papel | B16: Agressivo | C16: Papel | D16: 0.5
A17: =B17&"-"&C17 -> Agressivo-Tijolo | B17: Agressivo | C17: Tijolo | D17: 0.1
A18: =B18&"-"&C18 -> Agressivo-Híbridos | B18: Agressivo | C18: Híbridos | D18: 0.05
A19: =B19&"-"&C19 -> Agressivo-FOFs | B19: Agressivo | C19: FOFs | D19: 0.05
A20: =B20&"-"&C20 -> Agressivo-Desenvolvimento | B20: Agressivo | C20: Desenvolvimento | D20: 0.2
A21: =B21&"-"&C21 -> Agressivo-Hotelarias | B21: Agressivo | C21: Hotelarias | D21: 0.1
